Metadata-Version: 2.1
Name: pyqt5-applications
Version: 5.15.1
Summary: PyQt5开发工具/PyQt5  development tool
Home-page: https://yangguang-gongzuoshi.top/wry/
Author: Ruoyu Wang
Author-email: wry2022@outlook.com
License: MIT License
Platform: UNKNOWN
Requires: pathlib
